zipline_tej-2.2.1.dist-info/METADATA
zipline_tej-2.2.1.dist-info/LICENSE
zipline_tej-2.2.1.dist-info/top_level.txt
zipline_tej-2.2.1.dist-info/entry_points.txt
zipline_tej-2.2.1.dist-info/WHEEL
zipline_tej-2.2.1.dist-info/RECORD
zipline/algorithm.py
zipline/_protocol.pxd
zipline/_protocol.cpython-312-x86_64-linux-gnu.so
zipline/dispatch.py
zipline/api.pyi
zipline/test_algorithms.py
zipline/__main__.py
zipline/zipline_warnings.py
zipline/api.py
zipline/__init__.py
zipline/master.py
zipline/_version.py
zipline/errors.py
zipline/currency.py
zipline/extensions.py
zipline/_protocol.pyx
zipline/country.py
zipline/protocol.py
zipline/utils/functional.py
zipline/utils/cache.py
zipline/utils/calendar_utils.py
zipline/utils/api_info.py
zipline/utils/sqlite_utils.py
zipline/utils/factory.py
zipline/utils/idbox.py
zipline/utils/paths.py
zipline/utils/pandas_utils.py
zipline/utils/final.py
zipline/utils/math_utils.py
zipline/utils/compat.py
zipline/utils/events.py
zipline/utils/context_tricks.py
zipline/utils/preprocess.py
zipline/utils/dummy.py
zipline/utils/range.py
zipline/utils/numpy_utils.py
zipline/utils/__init__.py
zipline/utils/date_utils.py
zipline/utils/classproperty.py
zipline/utils/input_validation.py
zipline/utils/data.py
zipline/utils/api_support.py
zipline/utils/deprecate.py
zipline/utils/sharedoc.py
zipline/utils/memoize.py
zipline/utils/formatting.py
zipline/utils/cli.py
zipline/utils/argcheck.py
zipline/utils/string_formatting.py
zipline/utils/sentinel.py
zipline/utils/run_algo.py
zipline/utils/algo_instance.py
zipline/utils/security_list.py
zipline/utils/exploding_object.py
zipline/TQresearch/utils.py
zipline/TQresearch/futures_price.py
zipline/TQresearch/__init__.py
zipline/TQresearch/futures_smart_money_positions.py
zipline/TQresearch/futures_package.py
zipline/TQresearch/tej_pipeline.py
zipline/pipeline/domain.py
zipline/pipeline/visualize.py
zipline/pipeline/mixins.py
zipline/pipeline/engine.py
zipline/pipeline/__init__.py
zipline/pipeline/graph.py
zipline/pipeline/api_utils.py
zipline/pipeline/sentinels.py
zipline/pipeline/term.py
zipline/pipeline/common.py
zipline/pipeline/expression.py
