Metadata-Version: 2.1
Name: zipline-tej
Version: 2.2.1
Summary: A Pythonic backtester for trading algorithms
Author: tej
Author-email: tej@tej.com.tw
Maintainer: tej api Development Team
Maintainer-email: tej@tej.com.tw
License: Apache-2.0
Project-URL: homepage, https://tquant.tejwin.com/
Project-URL: repository, https://github.com/tejtw/zipline-tej
Classifier: Development Status :: 4 - Beta
Classifier: License :: OSI Approved :: Apache Software License
Classifier: Natural Language :: English
Classifier: Programming Language :: Python
Classifier: Programming Language :: Python :: 3.9
Classifier: Programming Language :: Python :: 3.10
Classifier: Programming Language :: Python :: 3.11
Classifier: Programming Language :: Python :: 3.12
Classifier: Operating System :: OS Independent
Classifier: Intended Audience :: Science/Research
Classifier: Topic :: Office/Business :: Financial :: Investment
Classifier: Topic :: Scientific/Engineering :: Information Analysis
Classifier: Topic :: System :: Distributed Computing
Requires-Python: >=3.9
Provides-Extra: test
Provides-Extra: dev
Provides-Extra: docs
License-File: LICENSE
